{
  "strategic": {
    "regime": "SIDEWAYS",
    "reason": "SIDEWAYS",
    "last_update": "2026-01-07T16:40:06.818440"
  },
  "news": {
    "sentiment": 0.0354,
    "latest_headline": "\ud83d\ude10 Neutral market. Follow technical signals.",
    "count": 12,
    "last_update": "2026-01-07T16:43:31.132470"
  },
  "market": {
    "chop_index": {
      "BTCUSDT": 47.02074305481673,
      "SOLUSDT": 54.86487462692381
    },
    "rsi_values": {
      "BTCUSDT": 55.1,
      "SOLUSDT": 37.72
    },
    "current_prices": {
      "BTCUSDT": 92141.0,
      "SOLUSDT": 137.96
    }
  },
  "ml_predictions": {
    "BTCUSDT": {
      "decision": "SELL",
      "confidence": 0.55,
      "change_pct": -0.5,
      "timestamp": "2026-01-07T16:43:31.346077"
    },
    "SOLUSDT": {
      "decision": "HOLD",
      "confidence": 0.3,
      "change_pct": -0.007868957618484274,
      "timestamp": "2026-01-07T16:40:09.844251"
    }
  },
  "gatekeeper": {
    "BTCUSDT": "SKIP: Mean Reversion: RSI neutral (54.1) - waiting for extremes",
    "SOLUSDT": "SKIP: Mean Reversion: RSI neutral (41.3) - waiting for extremes"
  },
  "decision_reasoning": {},
  "positions": {
    "active": [],
    "count": 0
  },
  "system": {
    "bot_running": true,
    "last_scan": "2026-01-07T16:43:27.503066",
    "total_decisions": 17
  },
  "performance": {
    "total_trades": 652,
    "winning_trades": 199,
    "losing_trades": 453,
    "win_rate": 30.52147239263804,
    "total_pnl": 89.9797599999995,
    "current_balance": 100.0,
    "performance_24h": -0.06399999999999861
  },
  "recent_trades": [],
  "price_changes_24h": {},
  "volumes": {},
  "ai_reasoning": {
    "strategic_text": "\ud83e\udde0 STRATEGIC BRAIN ANALYSIS (Updated: 16:40:06)\n\nMarket Regime: SIDEWAYS\n\nAI Gateway Analysis:\nSIDEWAYS\n\nTrading Strategy:\n\u2192 Both LONG and SHORT allowed\n\u2192 Range-bound market, normal trading conditions\n\nLast BTC Price: $92133.90\nNext Update: 0.25h or \u00b13.0% BTC move",
    "news_analysis": "\ud83d\udcf0 NEWS ANALYSIS (BTCUSDT)\n\nSentiment Score: 0.035 (NEUTRAL)\nNews Count: 12 articles analyzed\n\nRecommendation:\n\ud83d\ude10 Neutral market. Follow technical signals.\n\nImpact Assessment:\n\ud83d\ude10 NEUTRAL - No strong sentiment\n\u2192 Follow technical signals"
  },
  "decision_flow": {
    "step_0_strategic": {
      "status": "pending",
      "result": null,
      "time_ms": 0
    },
    "step_1_trading_hours": {
      "status": "pending",
      "result": null,
      "time_ms": 0
    },
    "step_2_chop_filter": {
      "status": "pending",
      "result": null,
      "time_ms": 0
    },
    "step_3_pattern_filter": {
      "status": "pending",
      "result": null,
      "time_ms": 0
    },
    "step_4_ml_confidence": {
      "status": "pending",
      "result": null,
      "time_ms": 0
    },
    "step_5_fee_check": {
      "status": "pending",
      "result": null,
      "time_ms": 0
    },
    "step_6_futures_brain": {
      "status": "pending",
      "result": null,
      "time_ms": 0
    },
    "final_decision": {
      "action": "SKIP",
      "reason": "Not analyzed yet"
    }
  }
}